sergiu_dyno/__init__.py
sergiu_dyno-0.5.0.dist-info/METADATA
sergiu_dyno-0.5.0.dist-info/WHEEL
sergiu_dyno-0.5.0.dist-info/top_level.txt
sergiu_dyno-0.5.0.dist-info/RECORD
