Metadata-Version: 2.1
Name: sergiu-dyno
Version: 0.5.0
Summary: Prints a dinosaur
Home-page: UNKNOWN
Author: Matei Sergiu
Author-email: mateisergiu777@gmail.com
License: UNKNOWN
Platform: UNKNOWN
Requires-Dist: dinosay
